foss505/__init__.py
foss505/__main__.py
foss505/exceptions.py
foss505/jackclient.py
foss505/loop.py
foss505/observable.py
foss505/station.py
foss505/ui/__init__.py
foss505/ui/assets/fonts/KaushanScript-Regular.ttf
foss505/ui/assets/images/inactive.png
foss505/ui/assets/images/logo.png
foss505/ui/assets/images/muted.png
foss505/ui/assets/images/overdub.png
foss505/ui/assets/images/play.png
foss505/ui/assets/images/recording.png
foss505/ui/get_asset.py
foss505/ui/loopbutton.py
foss505/ui/loopchannel.py
foss505/ui/volumebar.py
foss505-0.1.0a0.dist-info/LICENSE
foss505-0.1.0a0.dist-info/METADATA
foss505-0.1.0a0.dist-info/WHEEL
foss505-0.1.0a0.dist-info/entry_points.txt
foss505-0.1.0a0.dist-info/RECORD
