Metadata-Version: 2.1
Name: foss505
Version: 0.1.0a0
Summary: The ultimate loop station.
Home-page: https://github.com/ramazanemreosmanoglu/foss505
License: GPL-3.0-only
Author: ramazanemreosmanoglu
Author-email: ramazanemre@protonmail.com
Requires-Python: >=3.10,<4.0
Classifier: License :: OSI Approved :: GNU General Public License v3 (GPLv3)
Classifier: Programming Language :: Python :: 3
Classifier: Programming Language :: Python :: 3.10
Classifier: Programming Language :: Python :: 3.11
Requires-Dist: PySide6 (==6.4.1) ; python_version >= "3.10" and python_version < "3.12"
Requires-Dist: jack-client (>=0.5.4,<0.6.0)
Requires-Dist: numpy (>=1.24.1,<2.0.0)
Project-URL: Repository, https://github.com/ramazanemreosmanoglu/foss505
